{
  "meta": {
    "id": "dk-el-net-kongerslev-nettarif-c",
    "schemaVersion": "1",
    "country": "DK",
    "distributor": "El-net Kongerslev A/S",
    "provider": "El-net Kongerslev",
    "plan": "Nettarif C",
    "currency": "DKK",
    "unit": "kWh",
    "timezone": "Europe/Copenhagen",
    "source": "provider",
    "sourceUrl": "https://www.energidataservice.dk/tso-electricity/DatahubPricelist",
    "license": "CC-BY-4.0",
    "updated": "2026-06-24",
    "verified": false,
    "notes": "Danish DSO/TSO network tariff component — the per-kWh grid charge applied by hour — from Energinet's Energi Data Service \"DatahubPricelist\" dataset. Licensed CC BY 4.0; attribute Energinet / Energi Data Service. This is the NETWORK charge, not a full retail plan."
  },
  "tariff": {
    "kind": "flat",
    "import": {
      "flatRate": 0.4
    },
    "validFrom": "2023-02-01"
  }
}
