{
  "meta": {
    "id": "ch-politische-gemeinde-dietlikon-gemeindewerke-standard-supply-household-h4",
    "schemaVersion": "1",
    "country": "CH",
    "distributor": "Politische Gemeinde Dietlikon, Gemeindewerke",
    "provider": "Politische Gemeinde Dietlikon, Gemeindewerke",
    "plan": "Standard supply (household H4)",
    "currency": "CHF",
    "unit": "kWh",
    "timezone": "Europe/Zurich",
    "source": "provider",
    "sourceUrl": "https://www.strompreis.elcom.admin.ch/",
    "license": "other",
    "updated": "2026-06-22",
    "verified": false,
    "notes": "Swiss household electricity tariff — ElCom reference profile H4 (~4,500 kWh/yr), basic/standard supply (Grundversorgung) — from the Federal Electricity Commission (ElCom) via LINDAS (lindas.admin.ch). opendata.swiss \"Open use\" (terms_open); ElCom attributed as a courtesy. All-in 23.52 Rp/kWh = energy 12.78 + grid 7.05 + federal grid surcharge 2.30 + community/cantonal taxes; annual fixed 0 CHF. Serves 1 municipality. Period 2026."
  },
  "tariff": {
    "kind": "flat",
    "import": {
      "flatRate": 0.23516
    },
    "validFrom": "2026-01-01"
  }
}
